quantops/__init__.py
quantops/core.py
quantops/generate.py
quantops/parser.py
quantops/registry.toml
quantops-0.3.0.dist-info/METADATA
quantops-0.3.0.dist-info/WHEEL
quantops-0.3.0.dist-info/top_level.txt
quantops-0.3.0.dist-info/RECORD
